kilroy_face_server_py_sdk/__init__.py
kilroy_face_server_py_sdk/face.py
kilroy_face_server_py_sdk/resources/__init__.py
kilroy_face_server_py_sdk/server.py
kilroy_face_server_py_sdk/service.py
kilroy_face_server_py_sdk/state.py
kilroy_face_server_py_sdk-0.9.0.dist-info/LICENSE
kilroy_face_server_py_sdk-0.9.0.dist-info/WHEEL
kilroy_face_server_py_sdk-0.9.0.dist-info/METADATA
kilroy_face_server_py_sdk-0.9.0.dist-info/RECORD
