Metadata-Version: 2.1
Name: kilroy-face-server-py-sdk
Version: 0.9.0
Summary: SDK for kilroy face servers in Python 🧰
Home-page: https://github.com/kilroybot/kilroy-face-server-py-sdk
Author: kilroy
Author-email: kilroymail@pm.me
Requires-Python: >=3.10,<4.0
Classifier: License :: OSI Approved :: MIT License
Classifier: Operating System :: OS Independent
Classifier: Programming Language :: Python :: 3
Classifier: Programming Language :: Python :: 3.10
Requires-Dist: kilroy-face-py-shared (>=0.6,<0.7)
Requires-Dist: kilroy-server-py-utils (>=0.4,<0.5)
Project-URL: Documentation, https://kilroybot.github.io/kilroy-face-server-py-sdk
Project-URL: Repository, https://github.com/kilroybot/kilroy-face-server-py-sdk
